opensearch_benchmark-2.1.0.data/scripts/expand-data-corpus.py
opensearch_benchmark-2.1.0.data/scripts/pbzip2
opensearch_benchmark-2.1.0.dist-info/licenses/AUTHORS
opensearch_benchmark-2.1.0.dist-info/licenses/LICENSE
opensearch_benchmark-2.1.0.dist-info/licenses/NOTICE
osbenchmark/__init__.py
osbenchmark/actor.py
osbenchmark/aggregator.py
osbenchmark/async_connection.py
osbenchmark/benchmark.py
osbenchmark/benchmarkd.py
osbenchmark/client.py
osbenchmark/config.py
osbenchmark/context.py
osbenchmark/exceptions.py
osbenchmark/kafka_client.py
osbenchmark/log.py
osbenchmark/metrics.py
osbenchmark/min-os-version.txt
osbenchmark/paths.py
osbenchmark/publisher.py
osbenchmark/telemetry.py
osbenchmark/test_run_orchestrator.py
osbenchmark/time.py
osbenchmark/version.py
osbenchmark/builder/__init__.py
osbenchmark/builder/builder.py
osbenchmark/builder/cluster.py
osbenchmark/builder/cluster_builder.py
osbenchmark/builder/cluster_config.py
osbenchmark/builder/java_resolver.py
osbenchmark/builder/launcher.py
osbenchmark/builder/provisioner.py
osbenchmark/builder/supplier.py
osbenchmark/builder/configs/__init__.py
osbenchmark/builder/configs/listers/__init__.py
osbenchmark/builder/configs/listers/plugin_config_instance_lister.py
osbenchmark/builder/configs/utils/__init__.py
osbenchmark/builder/configs/utils/config_path_resolver.py
osbenchmark/builder/downloaders/__init__.py
osbenchmark/builder/downloaders/core_plugin_source_downloader.py
osbenchmark/builder/downloaders/downloader.py
osbenchmark/builder/downloaders/external_plugin_source_downloader.py
osbenchmark/builder/downloaders/opensearch_distribution_downloader.py
osbenchmark/builder/downloaders/opensearch_source_downloader.py
osbenchmark/builder/downloaders/plugin_distribution_downloader.py
osbenchmark/builder/downloaders/builders/__init__.py
osbenchmark/builder/downloaders/builders/binary_builder.py
osbenchmark/builder/downloaders/builders/source_binary_builder.py
osbenchmark/builder/downloaders/repositories/__init__.py
osbenchmark/builder/downloaders/repositories/opensearch_distribution_repository_provider.py
opensearch_benchmark-2.1.0.dist-info/METADATA
opensearch_benchmark-2.1.0.dist-info/WHEEL
opensearch_benchmark-2.1.0.dist-info/entry_points.txt
opensearch_benchmark-2.1.0.dist-info/top_level.txt
opensearch_benchmark-2.1.0.dist-info/RECORD
